exergenicslayers/exergenicslayers.py
exergenicslayers-1.8.dist-info/METADATA
exergenicslayers-1.8.dist-info/WHEEL
exergenicslayers-1.8.dist-info/top_level.txt
exergenicslayers-1.8.dist-info/RECORD
