Metadata-Version: 2.1
Name: exergenicslayers
Version: 1.8
Summary: UNKNOWN
Home-page: https://github.com/Exergenics/internal-portal-api-lambda
Author: Sanjeevani Avasthi
Author-email: sanjeevani.avasthi@exergenics.com
License: UNKNOWN
Keywords: exergenics portal layer api
Platform: UNKNOWN
Requires-Dist: boto3
Requires-Dist: datetime
Requires-Dist: requests
Requires-Dist: urllib3
